<?xml version = '1.0' encoding = 'UTF-8'?>
<SegmentOraclev10g class="oracle.dbtools.crest.model.design.storage.oracle.v10g.SegmentOraclev10g" name="Storage12" directorySegmentName="seg_0" id="CC3553EA-F4B9-8356-B25A-0D148B08DEB5">
<createdBy>ley</createdBy>
<createdTime>2016-07-20 16:17:24 UTC</createdTime>
<ownerDesignName>InmobiliariaBD_DDL</ownerDesignName>
<initrans>2</initrans>
<scInitialExtent>65536</scInitialExtent>
<scMaxExtents>2147483645</scMaxExtents>
<scNextExtent>1048576</scNextExtent>
</SegmentOraclev10g>